capfinder/__init__.py
capfinder/align.py
capfinder/attention_cnnlstm_model.py
capfinder/bam.py
capfinder/cli.py
capfinder/cnn_lstm_model.py
capfinder/collate.py
capfinder/constants.py
capfinder/cyclic_learing_rate.py
capfinder/data_loader.py
capfinder/download_model.py
capfinder/encoder_model.py
capfinder/find_ote_test.py
capfinder/find_ote_train.py
capfinder/index.py
capfinder/inference.py
capfinder/inference_data_loader.py
capfinder/logger_config.py
capfinder/ml_libs.py
capfinder/model/__init__.py
capfinder/model/cnn_lstm-classifier.keras
capfinder/model/v1.2.0
capfinder/plot.py
capfinder/process_pod5.py
capfinder/report.py
capfinder/resnet_model.py
capfinder/train_etl.py
capfinder/training.py
capfinder/upload_download.py
capfinder/utils.py
capfinder/visualize_alns.py
capfinder-0.4.3.dist-info/LICENCE
capfinder-0.4.3.dist-info/METADATA
capfinder-0.4.3.dist-info/WHEEL
capfinder-0.4.3.dist-info/entry_points.txt
capfinder-0.4.3.dist-info/RECORD
