Metadata-Version: 2.1
Name: capfinder
Version: 0.4.3
Summary: A package for decoding RNA cap types
Home-page: https://adnaniazi.github.io/capfinder
License: MIT
Author: Adnan M. Niazi
Author-email: adnaniazi@gmail.com
Requires-Python: >=3.10,<3.13
Classifier: Development Status :: 4 - Beta
Classifier: Intended Audience :: Developers
Classifier: License :: OSI Approved :: MIT License
Classifier: Operating System :: OS Independent
Classifier: Programming Language :: Python
Classifier: Programming Language :: Python :: 3
Classifier: Programming Language :: Python :: 3.10
Classifier: Programming Language :: Python :: 3.11
Classifier: Programming Language :: Python :: 3.12
Classifier: Topic :: Software Development :: Libraries :: Python Modules
Classifier: Typing :: Typed
Provides-Extra: cpu
Provides-Extra: gpu
Provides-Extra: tpu
Requires-Dist: biopython (>=1.83,<2.0)
Requires-Dist: bokeh (>=3.3.0,<4.0.0)
Requires-Dist: comet-ml (>=3.39.3,<4.0.0)
Requires-Dist: hpack (>=4.0.0,<5.0.0)
Requires-Dist: httpx (>=0.27.0,<0.28.0)
Requires-Dist: imbalanced-learn (>=0.12.3,<0.13.0)
Requires-Dist: jax ; extra == "cpu" or extra == "gpu" or extra == "tpu"
Requires-Dist: keras (>=3.3.2,<4.0.0)
Requires-Dist: keras-tuner (>=1.4.7,<2.0.0)
Requires-Dist: loguru (>=0.7.2,<0.8.0)
Requires-Dist: matplotlib (>=3.8.0,<4.0.0)
Requires-Dist: mpire (>=2.8.0,<3.0.0)
Requires-Dist: parasail (>=1.3.4,<2.0.0)
Requires-Dist: pod5 (>=0.3.10,<0.4.0)
Requires-Dist: polars (>=0.20.21,<0.21.0)
Requires-Dist: pre-commit (>=3.7.0,<4.0.0)
Requires-Dist: prefect (>=2.18.3,<3.0.0)
Requires-Dist: prefect-dask (>=0.2.8,<0.3.0)
Requires-Dist: pysam (>=0.22.1,<0.23.0)
Requires-Dist: pytest-mock (>=3.11.1,<4.0.0)
Requires-Dist: scikit-learn (>=1.4.2,<2.0.0)
Requires-Dist: tensorflow (>=2.16.1,<3.0.0)
Requires-Dist: toml (>=0.10.2,<0.11.0)
Requires-Dist: tqdm (>=4.66.1,<5.0.0)
Requires-Dist: typer (>=0.12.3,<0.13.0)
Requires-Dist: types-toml (>=0.10.8.7,<0.11.0.0)
Requires-Dist: types-tqdm (>=4.66.0.20240106,<5.0.0.0)
Project-URL: Documentation, https://adnaniazi.github.io/capfinder
Project-URL: Repository, https://github.com/adnaniazi/capfinder
